PartNLP/__init__.py
PartNLP/core.py
PartNLP/interface.py
PartNLP/main.py
PartNLP/models/__init__.py
PartNLP/models/helper/__init__.py
PartNLP/models/helper/color.py
PartNLP/models/helper/configuration.py
PartNLP/models/helper/constants.py
PartNLP/models/helper/logger.py
PartNLP/models/helper/profiling.py
PartNLP/models/helper/program_profiling.py
PartNLP/models/helper/progress_bar.py
PartNLP/models/helper/time_and_usage_profiling.py
PartNLP/models/helper/utils.py
PartNLP/models/helper/readers_and_writers/__init__.py
PartNLP/models/helper/readers_and_writers/json_reader_and_writer.py
PartNLP/models/helper/readers_and_writers/reader_and_writer.py
PartNLP/models/helper/readers_and_writers/txt_reader_and_writer.py
PartNLP/models/pre_processors/__init__.py
PartNLP/models/pre_processors/hazm_preprocessor.py
PartNLP/models/pre_processors/parsivar_preprocessor.py
PartNLP/models/pre_processors/preprocess.py
PartNLP/models/pre_processors/stanza_preprocessor.py
PartNLP/models/validation/__init__.py
PartNLP/models/validation/config_validator.py
PartNLP/models/validation/language_validator.py
PartNLP/models/validation/lemmatize_validator.py
PartNLP/models/validation/normalize_validator.py
PartNLP/models/validation/package_validator.py
PartNLP/models/validation/pos_validator.py
PartNLP/models/validation/processor_validator.py
PartNLP/models/validation/sent_validator.py
PartNLP/models/validation/stem_validator.py
PartNLP/models/validation/validator.py
PartNLP/models/validation/word_validator.py
PartNLP/models/validators/__init__.py
PartNLP/models/validators/config_validator.py
PartNLP/models/validators/file_format_validator.py
PartNLP/models/validators/language_validator.py
PartNLP/models/validators/lemmatize_validator.py
PartNLP/models/validators/multi_process_validator.py
PartNLP/models/validators/normalize_validator.py
PartNLP/models/validators/package_validator.py
PartNLP/models/validators/pos_validator.py
PartNLP/models/validators/processor_validator.py
PartNLP-0.1.34.dist-info/LICENSE
PartNLP-0.1.34.dist-info/METADATA
PartNLP-0.1.34.dist-info/WHEEL
PartNLP-0.1.34.dist-info/top_level.txt
PartNLP-0.1.34.dist-info/RECORD
