Metadata-Version: 2.1
Name: PartNLP
Version: 0.1.34
Summary: A Python NLP Library for Persian language, by PartDP AI
Home-page: https://github.com/partdpai/PartNLP
Author: Part DP
Author-email: info@partdp.ai
License: UNKNOWN
Keywords: natural-language-processing nlp natural-language-understanding
Platform: UNKNOWN
Classifier: Intended Audience :: Developers
Classifier: Intended Audience :: Education
Classifier: Intended Audience :: Science/Research
Classifier: Intended Audience :: Information Technology
Classifier: Topic :: Scientific/Engineering
Classifier: Topic :: Scientific/Engineering :: Artificial Intelligence
Classifier: Topic :: Scientific/Engineering :: Information Analysis
Classifier: Topic :: Text Processing
Classifier: Topic :: Text Processing :: Linguistic
Classifier: Topic :: Software Development
Classifier: Topic :: Software Development :: Libraries
Classifier: Programming Language :: Python :: 3
Classifier: License :: OSI Approved :: MIT License
Classifier: Operating System :: OS Independent
Requires-Python: >=3.7
Requires-Dist: hazm
Requires-Dist: parsivar
Requires-Dist: stanza
Requires-Dist: nltk
Requires-Dist: dash
Requires-Dist: dash-bootstrap-components
Requires-Dist: terminaltables
Requires-Dist: psutil
